vupi/__init__.py
vupi/main.py
vupi-0.0.1.dist-info/METADATA
vupi-0.0.1.dist-info/WHEEL
vupi-0.0.1.dist-info/RECORD
